django_currentuser/__init__.py
django_currentuser/middleware.py
django_currentuser/db/__init__.py
django_currentuser/db/models/__init__.py
django_currentuser/db/models/fields.py
django_currentuser-0.10.0.dist-info/licenses/LICENSE
django_currentuser-0.10.0.dist-info/METADATA
django_currentuser-0.10.0.dist-info/WHEEL
django_currentuser-0.10.0.dist-info/top_level.txt
django_currentuser-0.10.0.dist-info/RECORD
