Metadata-Version: 2.4
Name: django-currentuser
Version: 0.10.0
Summary: Conveniently store reference to request user on thread/db level.
Author-email: Peter Zsoldos <hello@zsoldosp.eu>
Maintainer-email: Peter Zsoldos <hello@zsoldosp.eu>
Project-URL: Homepage, https://github.com/zsoldosp/django-currentuser
Project-URL: Bug Tracker, https://github.com/zsoldosp/django-currentuser/issues
Classifier: Development Status :: 4 - Beta
Classifier: Intended Audience :: Developers
Classifier: License :: OSI Approved :: BSD License
Classifier: Operating System :: OS Independent
Classifier: Natural Language :: English
Classifier: Programming Language :: Python :: 3.10
Classifier: Programming Language :: Python :: 3.11
Classifier: Programming Language :: Python :: 3.12
Classifier: Programming Language :: Python :: 3.13
Classifier: Programming Language :: Python :: 3.14
Classifier: Framework :: Django
Classifier: Framework :: Django :: 4.2
Classifier: Framework :: Django :: 5.2
Classifier: Framework :: Django :: 6.0
Requires-Python: >=3.10
License-File: LICENSE
Requires-Dist: Django<6.1,>=4.2
Dynamic: license-file
Dynamic: requires-dist
